renkubio/__init__.py
renkubio/biosample.py
renkubio/cli.py
renkubio/common_entities.py
renkubio/rdf.py
renkubio/utils.py
renku_bio-0.2.0.dist-info/entry_points.txt
renku_bio-0.2.0.dist-info/WHEEL
renku_bio-0.2.0.dist-info/METADATA
renku_bio-0.2.0.dist-info/RECORD
