Metadata-Version: 2.1
Name: renku-bio
Version: 0.2.0
Summary: Renku plugin to annotate projects and datasets metadata with biological samples.
Home-page: https://renkulab.io/projects/cyril.matthey-doret/renku-bio
License: Apache-2.0
Keywords: Renku,CLI,biology,plugin,metadata
Author: cmdoret
Author-email: cyril.mattheydoret@gmail.com
Requires-Python: >=3.9,<4.0
Classifier: Development Status :: 3 - Alpha
Classifier: Intended Audience :: Education
Classifier: Intended Audience :: Science/Research
Classifier: License :: OSI Approved :: Apache Software License
Classifier: Operating System :: OS Independent
Classifier: Programming Language :: Python :: 3
Classifier: Programming Language :: Python :: 3.9
Classifier: Programming Language :: Python :: 3.10
Classifier: Programming Language :: Python :: 3.10
Classifier: Programming Language :: Python :: 3.8
Classifier: Programming Language :: Python :: 3.9
Classifier: Topic :: Scientific/Engineering :: Bio-Informatics
Requires-Dist: questionary (>=1.10.0,<2.0.0)
Requires-Dist: renku (>=1.8.0,<2.0.0)
Project-URL: Repository, https://renkulab.io/gitlab/cyril.matthey-doret/renku-bio
